setup.py
bin/lock-abort
bin/lock-block
django_locks/__init__.py
django_locks/decorators.py
django_locks/models.py
django_locks.egg-info/PKG-INFO
django_locks.egg-info/SOURCES.txt
django_locks.egg-info/dependency_links.txt
django_locks.egg-info/requires.txt
django_locks.egg-info/top_level.txt