Metadata-Version: 1.0
Name: django-locks
Version: 0.0.1
Summary: Database and filesystem locks for Django
Home-page: https://github.com/apn-online/django-locks
Author: Raymond Butcher
Author-email: randomy@gmail.com
License: MIT
Platform: UNKNOWN
